iautils/__init__.py
iautils/admin/__init__.py
iautils/admin/config.py
iautils/admin/dbio.py
iautils/admin/manager.py
iautils/audio/__init__.py
iautils/audio/transforms.py
iautils/audio/utils.py
iautils/audio/external/PyOctaveBand.py
iautils/audio/external/__init__.py
iautils/common/__init__.py
iautils/common/plot.py
iautils/common/utils.py
iautils/image/__init__.py
iautils/image/transforms.py
iautils/ml/__init__.py
iautils/ml/others.py
iautils-0.3.8.dist-info/METADATA
iautils-0.3.8.dist-info/WHEEL
iautils-0.3.8.dist-info/top_level.txt
iautils-0.3.8.dist-info/RECORD
