Metadata-Version: 2.1
Name: iautils
Version: 0.3.8
Summary: Image & Audio Common Utils
Home-page: http://mod.lge.com/hub/smartdata/iautils
Author: Woojin Cho
Author-email: lg.woojin.cho@lge.com
License: UNKNOWN
Download-URL: http://mod.lge.com/hub/smartdata/iautils/archive/0.3.8.tar.gz
Keywords: ia
Platform: UNKNOWN
Classifier: Programming Language :: Python :: 3
Classifier: Programming Language :: Python :: 3.6
Classifier: Programming Language :: Python :: 3.7
Classifier: Programming Language :: Python :: 3.8
Requires-Python: >=3
Requires-Dist: future (>=0.17.1)
Requires-Dist: PyYAML (>=5.1)
Requires-Dist: click (==7.1)
Requires-Dist: dask[complete]
Requires-Dist: pyarrow (==2.0)
Requires-Dist: matplotlib (==3.3)
Requires-Dist: tqdm (==4.54)
Requires-Dist: albumentations (>=0.5.2)
Requires-Dist: librosa (==0.8)
Requires-Dist: opencv-python (>=4.4)
Requires-Dist: nptdms (==1.1)
Requires-Dist: sqlalchemy (==1.3)
Requires-Dist: sqlalchemy-utils (>=0.36)
Requires-Dist: h5py (==3.1)
Requires-Dist: ruptures (>=1.1)
Requires-Dist: plotly (==4.14)
Requires-Dist: colorama (>=0.3.9)
Requires-Dist: si-prefix (>=1.2)
